odoo/addons/shipment_advice/README.rst
odoo/addons/shipment_advice/__init__.py
odoo/addons/shipment_advice/__manifest__.py
odoo/addons/shipment_advice/data/ir_sequence.xml
odoo/addons/shipment_advice/data/queue_job_channel.xml
odoo/addons/shipment_advice/data/queue_job_function.xml
odoo/addons/shipment_advice/demo/stock_dock.xml
odoo/addons/shipment_advice/i18n/es.po
odoo/addons/shipment_advice/i18n/fr.po
odoo/addons/shipment_advice/i18n/it.po
odoo/addons/shipment_advice/i18n/nl.po
odoo/addons/shipment_advice/i18n/pt_BR.po
odoo/addons/shipment_advice/i18n/shipment_advice.pot
odoo/addons/shipment_advice/models/__init__.py
odoo/addons/shipment_advice/models/res_company.py
odoo/addons/shipment_advice/models/res_config_settings.py
odoo/addons/shipment_advice/models/shipment_advice.py
odoo/addons/shipment_advice/models/stock_move.py
odoo/addons/shipment_advice/models/stock_move_line.py
odoo/addons/shipment_advice/models/stock_package_level.py
odoo/addons/shipment_advice/models/stock_picking.py
odoo/addons/shipment_advice/readme/CONTRIBUTORS.md
odoo/addons/shipment_advice/readme/DESCRIPTION.md
odoo/addons/shipment_advice/report/report_shipment_advice.xml
odoo/addons/shipment_advice/report/reports.xml
odoo/addons/shipment_advice/security/ir.model.access.csv
odoo/addons/shipment_advice/static/description/icon.png
odoo/addons/shipment_advice/static/description/index.html
odoo/addons/shipment_advice/tests/__init__.py
odoo/addons/shipment_advice/tests/common.py
odoo/addons/shipment_advice/tests/test_shipment_advice.py
odoo/addons/shipment_advice/tests/test_shipment_advice_async.py
odoo/addons/shipment_advice/tests/test_shipment_advice_auto_close.py
odoo/addons/shipment_advice/tests/test_shipment_advice_load.py
odoo/addons/shipment_advice/tests/test_shipment_advice_picking_values.py
odoo/addons/shipment_advice/tests/test_shipment_advice_plan.py
odoo/addons/shipment_advice/tests/test_shipment_advice_stock_user.py
odoo/addons/shipment_advice/tests/test_shipment_advice_to_load.py
odoo_addon_shipment_advice-18.0.1.2.1.2.dist-info/METADATA
odoo_addon_shipment_advice-18.0.1.2.1.2.dist-info/WHEEL
odoo_addon_shipment_advice-18.0.1.2.1.2.dist-info/top_level.txt
odoo_addon_shipment_advice-18.0.1.2.1.2.dist-info/RECORD
