Metadata-Version: 2.1
Name: odoo-addon-shipment_advice
Version: 18.0.1.2.1.2
Requires-Python: >=3.10
Requires-Dist: odoo-addon-queue_job==18.0.*
Requires-Dist: odoo-addon-stock_dock==18.0.*
Requires-Dist: odoo==18.0.*
Summary: Manage your (un)loading process through shipment advices.
Home-page: https://github.com/OCA/stock-logistics-transport
License: AGPL-3
Author: Camptocamp, BCIM, Odoo Community Association (OCA)
Author-email: support@odoo-community.org
Classifier: Programming Language :: Python
Classifier: Framework :: Odoo
Classifier: Framework :: Odoo :: 18.0
Classifier: License :: OSI Approved :: GNU Affero General Public License v3
